MANIFEST.in
requirements.txt
setup.py
poretools/Event.py
poretools/Fast5File.py
poretools/__init__.py
poretools/combine.py
poretools/events.py
poretools/fasta.py
poretools/fastq.py
poretools/formats.py
poretools/hist.py
poretools/index.py
poretools/metadata.py
poretools/nucdist.py
poretools/occupancy.py
poretools/organise.py
poretools/poretools_main.py
poretools/qual_v_pos.py
poretools/qualdist.py
poretools/readstats.py
poretools/squiggle.py
poretools/statistics.py
poretools/stats.py
poretools/tabular.py
poretools/times.py
poretools/version.py
poretools/winner.py
poretools/yield_plot.py
poretools.egg-info/PKG-INFO
poretools.egg-info/SOURCES.txt
poretools.egg-info/dependency_links.txt
poretools.egg-info/entry_points.txt
poretools.egg-info/not-zip-safe
poretools.egg-info/requires.txt
poretools.egg-info/top_level.txt
poretools/scripts/__init__.py
poretools/scripts/poretools
poretools/scripts/poretools-script.py